factorial_with_tail_call_optimization/__init__.py
factorial_with_tail_call_optimization/factorial.py
factorial_with_tail_call_optimization-1.0.dist-info/METADATA
factorial_with_tail_call_optimization-1.0.dist-info/WHEEL
factorial_with_tail_call_optimization-1.0.dist-info/licenses/LICENSE.txt
factorial_with_tail_call_optimization-1.0.dist-info/RECORD
